napari_bio_sample_data/__init__.py
napari_bio_sample_data/_sample_data.py
napari_bio_sample_data/napari.yaml
napari_bio_sample_data/__pycache__/__init__.cpython-39.pyc
napari_bio_sample_data/__pycache__/_sample_data.cpython-39.pyc
napari_bio_sample_data/_tests/__init__.py
napari_bio_sample_data/_tests/test_sample_data.py
napari_bio_sample_data/sample_images/.DS_Store
napari_bio_sample_data/sample_images/2D_timelapse.csv
napari_bio_sample_data/sample_images/2D_timelapse.tif
napari_bio_sample_data/sample_images/nuclei.tif
napari_bio_sample_data/sample_images/nuclei_label.tif
napari_bio_sample_data/sample_images/nuclei_surface.npz
napari_bio_sample_data/sample_images/skin.tif
napari_bio_sample_data/sample_images/skin_shape.csv
napari_bio_sample_data/sample_images/skin_shape.npy
napari_bio_sample_data/sample_images/timelapse_point.npy
napari_bio_sample_data/sample_images/timelapse_track.npy
napari_bio_sample_data/sample_images/tomo.tif
napari_bio_sample_data/sample_images/tomo_point.npy
napari_bio_sample_data/sample_images/tomo_vector.npy
napari_bio_sample_data-0.0.4.dist-info/LICENSE
napari_bio_sample_data-0.0.4.dist-info/METADATA
napari_bio_sample_data-0.0.4.dist-info/WHEEL
napari_bio_sample_data-0.0.4.dist-info/entry_points.txt
napari_bio_sample_data-0.0.4.dist-info/top_level.txt
napari_bio_sample_data-0.0.4.dist-info/RECORD
