Metadata-Version: 2.1
Name: napari-bio-sample-data
Version: 0.0.4
Summary: a sample data plugin for bio-related demos
Home-page: https://github.com/chili-chiu/napari-bio-sample-data
Author: Chi-Li Chiu
Author-email: cchiu@chanzuckerberg.com
License: BSD-3-Clause
Project-URL: Bug Tracker, https://github.com/chili-chiu/napari-bio-sample-data/issues
Project-URL: Documentation, https://github.com/chili-chiu/napari-bio-sample-data#README.md
Project-URL: Source Code, https://github.com/chili-chiu/napari-bio-sample-data
Project-URL: User Support, https://github.com/chili-chiu/napari-bio-sample-data/issues
Classifier: Development Status :: 2 - Pre-Alpha
Classifier: Intended Audience :: Developers
Classifier: Framework :: napari
Classifier: Topic :: Software Development :: Testing
Classifier: Programming Language :: Python
Classifier: Programming Language :: Python :: 3
Classifier: Programming Language :: Python :: 3.8
Classifier: Programming Language :: Python :: 3.9
Classifier: Programming Language :: Python :: 3.10
Classifier: Operating System :: OS Independent
Classifier: License :: OSI Approved :: BSD License
Requires-Python: >=3.8
License-File: LICENSE
Requires-Dist: numpy
Requires-Dist: fsspec
Requires-Dist: zarr (>=2.12.0)
Requires-Dist: dask
Requires-Dist: s3fs
Provides-Extra: testing
Requires-Dist: tox ; extra == 'testing'
Requires-Dist: pytest ; extra == 'testing'
Requires-Dist: pytest-cov ; extra == 'testing'
